{
  "main_complaint": "Dor de dente",
  "history_disease": "Cárie no terceiro dente de trás do lado esquerdo embaixo",
  "is_bleeding": "false",
  "is_allergic": "false",
  "is_infectious_rheumatism": "false",
  "is_cardiovascular_disorder": "false",
  "is_gastritis": "false",
  "is_diabetic": "false",
  "is_fainting": "false",
  "is_medical_treatment": "false",
  "is_medicines": "false",
  "is_operated": "false",
  "is_addictions": "false",
  "is_anxiety_or_depression": "false",
  "is_tuberculosis": "false",
  "is_syphilis": "false",
  "is_hepatitis": "false",
  "is_aids": "false",
  "is_measles": "false",
  "is_mumps": "false",
  "is_varicella": "false",
  "is_others": "false",
  "others": "",
  "is_smoker": "false",
  "smoking_frequency": "",
  "lips": "N",
  "alveolar_mucosa": "N",
  "mucosa_ugal": "N",
  "gums": "N",
  "tongue": "N",
  "salivary_glands": "N",
  "mouth_floor": "N",
  "lymph_nodes": "N",
  "hard_palate": "N",
  "atm": "N",
  "throat": "N",
  "chewing_muscles": "N",
  "soft_palate": "N",
  "occlusion": "N",
  "changes_found": "Foram encontradas outras cáries",
  "min_blood_pressure": "100 por 70",
  "max_blood_pressure": "120 por 80",
  "presumptive_diagnosis": "Diagnóstico presuntivo",
  "complementary_exams": "Exames complementares",
  "definitive_diagnosis": "Diagnóstico definitivo",
  "treatment": "Tratamento",
  "treatment_plan": "Plano de tratamento",
  "is_urgency": "false",
  "medication": "Medicação",
  "medication_description": "Descrição da medicação",
  "pacient_id": 1
}
